[
    {
        "car_id": 1,
        "customer_name": "John Doe",
        "email": "john@example.com",
        "phone": "+1234567890",
        "start_date": "2024-07-01",
        "end_date": "2024-07-05",
        "message": "Test booking from script",
        "id": 1,
        "created_at": "2025-06-30 18:11:11",
        "status": "pending"
    },
    {
        "car_id": 2,
        "customer_name": "Customer 1",
        "email": "customer1@example.com",
        "phone": "+1234567891",
        "start_date": "2024-07-06",
        "end_date": "2024-07-11",
        "message": "Booking 1",
        "id": 2,
        "created_at": "2025-06-30 18:17:17",
        "status": "pending"
    },
    {
        "car_id": 3,
        "customer_name": "Customer 2",
        "email": "customer2@example.com",
        "phone": "+1234567892",
        "start_date": "2024-07-07",
        "end_date": "2024-07-12",
        "message": "Booking 2",
        "id": 3,
        "created_at": "2025-06-30 18:17:17",
        "status": "pending"
    },
    {
        "car_id": 4,
        "customer_name": "Customer 3",
        "email": "customer3@example.com",
        "phone": "+1234567893",
        "start_date": "2024-07-08",
        "end_date": "2024-07-13",
        "message": "Booking 3",
        "id": 4,
        "created_at": "2025-06-30 18:17:17",
        "status": "pending"
    },
    {
        "car_id": 2,
        "customer_name": "Jos\u00e9 Mar\u00eda O'Connor-Smith",
        "email": "jose.maria@example.com",
        "phone": "+34-123-456-789",
        "start_date": "2024-08-01",
        "end_date": "2024-08-05",
        "message": "Special chars: \u00e0\u00e1\u00e2\u00e3\u00e4\u00e5\u00e6\u00e7\u00e8\u00e9\u00ea\u00eb & symbols!",
        "id": 5,
        "created_at": "2025-06-30 18:17:17",
        "status": "pending"
    },
    {
        "car_id": 1,
        "customer_name": "Website Test User",
        "email": "website@test.com",
        "phone": "+1234567890",
        "start_date": "2025-07-01",
        "end_date": "2025-07-07",
        "message": "Test booking from website simulation",
        "id": 6,
        "created_at": "2025-06-30 18:23:24",
        "status": "pending"
    },
    {
        "car_id": 1,
        "customer_name": "John Smith",
        "email": "john.smith@example.com",
        "phone": "+1234567890",
        "start_date": "2025-07-01",
        "end_date": "2025-07-09",
        "message": "Test booking from form",
        "id": 7,
        "created_at": "2025-06-30 18:25:55",
        "status": "pending"
    },
    {
        "car_id": 4,
        "customer_name": "John Smith",
        "email": "john.smith@example.com",
        "phone": "+1234567890",
        "start_date": "2025-07-01",
        "end_date": "2025-07-31",
        "message": "Test booking",
        "id": 8,
        "created_at": "2025-06-30 18:34:49",
        "status": "pending"
    },
    {
        "car_id": 4,
        "customer_name": "John Smith",
        "email": "john.smith@example.com",
        "phone": "+1234567890",
        "start_date": "2025-07-01",
        "end_date": "2025-07-31",
        "message": "Test booking",
        "id": 9,
        "created_at": "2025-06-30 19:21:46",
        "status": "pending"
    },
    {
        "car_id": 4,
        "customer_name": "John Smith",
        "email": "john.smith@example.com",
        "phone": "+1234567890",
        "start_date": "2025-07-01",
        "end_date": "2025-07-31",
        "message": "Test booking",
        "id": 10,
        "created_at": "2025-06-30 19:21:48",
        "status": "pending"
    },
    {
        "car_id": 4,
        "customer_name": "John Smith",
        "email": "john.smith@example.com",
        "phone": "+1234567890",
        "start_date": "2025-07-01",
        "end_date": "2025-07-31",
        "message": "Test booking",
        "id": 11,
        "created_at": "2025-06-30 19:53:09",
        "status": "pending"
    }
]